MANIFEST.in
README.md
setup.py
shap/__init__.py
shap/__main__.py
shap/_explanation.py
shap/beImported.py
shap/datasets.py
shap/links.py
shap/toImport.py
shap/actions/__init__.py
shap/actions/_action.py
shap/actions/_optimizer.py
shap/benchmark/__init__.py
shap/benchmark/experiments.py
shap/benchmark/framework.py
shap/benchmark/measures.py
shap/benchmark/methods.py
shap/benchmark/metrics.py
shap/benchmark/models.py
shap/benchmark/perturbation.py
shap/benchmark/plots.py
shap/cext/_cext.cc
shap/cext/tree_shap.h
shap/explainers/__init__.py
shap/explainers/_additive.py
shap/explainers/_exact.py
shap/explainers/_explainer.py
shap/explainers/_gpu_tree.py
shap/explainers/_gradient.py
shap/explainers/_kernel.py
shap/explainers/_linear.py
shap/explainers/_partition.py
shap/explainers/_permutation.py
shap/explainers/_sampling.py
shap/explainers/_tree.py
shap/explainers/mimic.py
shap/explainers/pytree.py
shap/explainers/tf_utils.py
shap/explainers/_deep/__init__.py
shap/explainers/_deep/deep_pytorch.py
shap/explainers/_deep/deep_tf.py
shap/explainers/other/__init__.py
shap/explainers/other/_coefficent.py
shap/explainers/other/_lime.py
shap/explainers/other/_maple.py
shap/explainers/other/_random.py
shap/explainers/other/_treegain.py
shap/maskers/__init__.py
shap/maskers/_composite.py
shap/maskers/_fixed.py
shap/maskers/_fixed_composite.py
shap/maskers/_image.py
shap/maskers/_masker.py
shap/maskers/_tabular.py
shap/maskers/_text.py
shap/models/__init__.py
shap/models/_generate_topk_lm.py
shap/models/_model.py
shap/models/_pt_generate_topk_lm.py
shap/models/_pt_teacher_forcing_logits.py
shap/models/_pt_text_generation.py
shap/models/_teacher_forcing_logits.py
shap/models/_tf_generate_topk_lm.py
shap/models/_tf_teacher_forcing_logits.py
shap/models/_tf_text_generation.py
shap/models_uploaders/__init__.py
shap/models_uploaders/_sk_uploader.py
shap/plots/__init__.py
shap/plots/_bar.py
shap/plots/_beeswarm.py
shap/plots/_decision.py
shap/plots/_embedding.py
shap/plots/_force.py
shapresearchable.egg-info/PKG-INFO
shapresearchable.egg-info/SOURCES.txt
shapresearchable.egg-info/dependency_links.txt
shapresearchable.egg-info/not-zip-safe
shapresearchable.egg-info/requires.txt
shapresearchable.egg-info/top_level.txt